benchloop/__init__.py
benchloop/benchmarker.py
benchloop/dataset_exporter.py
benchloop/db_manager.py
benchloop/loader.py
benchloop/prompt_runner.py
benchloop/__pycache__/__init__.cpython-313.pyc
benchloop/__pycache__/benchmarker.cpython-313.pyc
benchloop/__pycache__/dataset_exporter.cpython-313.pyc
benchloop/__pycache__/db_manager.cpython-313.pyc
benchloop/__pycache__/loader.cpython-313.pyc
benchloop/__pycache__/prompt_runner.cpython-313.pyc
benchloop/benchloop.egg-info/PKG-INFO
benchloop/benchloop.egg-info/SOURCES.txt
benchloop/benchloop.egg-info/dependency_links.txt
benchloop/benchloop.egg-info/requires.txt
benchloop/benchloop.egg-info/top_level.txt
benchloop-0.1.1.dist-info/licenses/LICENSE
benchloop-0.1.1.dist-info/METADATA
benchloop-0.1.1.dist-info/WHEEL
benchloop-0.1.1.dist-info/top_level.txt
benchloop-0.1.1.dist-info/RECORD
