Metadata-Version: 2.4
Name: benchloop
Version: 0.1.1
Summary: A Python library for managing, processing, and benchmarking datasets in SQLite databases for AI pipelines and LLM prompt engineering.
Author-email: Elias Tsoukatos <elias@merlinaifoundation.org>
License:                     GNU AFFERO GENERAL PUBLIC LICENSE
Project-URL: Homepage, https://github.com/merlinaifoundation/benchloop
Project-URL: Documentation, https://github.com/merlinaifoundation/benchloop/blob/main/docs/benchloop.md
Project-URL: Source, https://github.com/merlinaifoundation/benchloop
Classifier: Programming Language :: Python :: 3
Classifier: License :: OSI Approved :: MIT License
Classifier: Operating System :: OS Independent
Classifier: Intended Audience :: Developers
Classifier: Intended Audience :: Science/Research
Classifier: Topic :: Software Development :: Libraries
Classifier: Topic :: Scientific/Engineering :: Artificial Intelligence
Requires-Python: >=3.7
License-File: LICENSE
Requires-Dist: openai
Dynamic: license-file
